{"remainingRequest":"/Users/julien/workspace/jhipster-automation/samples/jhipster-sample-app-react/node_modules/thread-loader/dist/cjs.js??ref--4-2!/Users/julien/workspace/jhipster-automation/samples/jhipster-sample-app-react/node_modules/ts-loader/index.js??ref--4-3!/Users/julien/workspace/jhipster-automation/samples/jhipster-sample-app-react/node_modules/tslint-loader/index.js!/Users/julien/workspace/jhipster-automation/samples/jhipster-sample-app-react/src/main/webapp/app/modules/home/home.tsx","dependencies":[{"path":"/Users/julien/workspace/jhipster-automation/samples/jhipster-sample-app-react/src/main/webapp/app/modules/home/home.tsx","mtime":1522786296946},{"path":"/Users/julien/workspace/jhipster-automation/samples/jhipster-sample-app-react/node_modules/react-hot-loader/webpack.js","mtime":1505850161000},{"path":"/Users/julien/workspace/jhipster-automation/samples/jhipster-sample-app-react/node_modules/cache-loader/dist/cjs.js","mtime":0},{"path":"/Users/julien/workspace/jhipster-automation/samples/jhipster-sample-app-react/node_modules/thread-loader/dist/cjs.js","mtime":0},{"path":"/Users/julien/workspace/jhipster-automation/samples/jhipster-sample-app-react/node_modules/ts-loader/index.js","mtime":1521265445000},{"path":"/Users/julien/workspace/jhipster-automation/samples/jhipster-sample-app-react/node_modules/tslint-loader/index.js","mtime":1519899048000}],"contextDependencies":[],"result":["\"use strict\";\nObject.defineProperty(exports, \"__esModule\", { value: true });\nvar tslib_1 = require(\"tslib\");\nrequire(\"./home.css\");\nvar React = require(\"react\");\nvar react_router_dom_1 = require(\"react-router-dom\");\nvar react_jhipster_1 = require(\"react-jhipster\");\nvar react_redux_1 = require(\"react-redux\");\nvar authentication_1 = require(\"app/shared/reducers/authentication\");\nvar Home = /** @class */ (function (_super) {\n    tslib_1.__extends(Home, _super);\n    function Home() {\n        var _this = _super !== null && _super.apply(this, arguments) || this;\n        _this.state = {\n            currentUser: _this.props.account\n        };\n        return _this;\n    }\n    Home.prototype.componentWillMount = function () {\n        this.props.getSession();\n    };\n    Home.prototype.componentWillReceiveProps = function (nextProps) {\n        this.setState({\n            currentUser: nextProps.account\n        });\n    };\n    Home.prototype.render = function () {\n        var currentUser = this.state.currentUser;\n        return (React.createElement(\"div\", { className: \"row\" },\n            React.createElement(\"div\", { className: \"col-md-9\" },\n                React.createElement(\"h2\", null,\n                    React.createElement(react_jhipster_1.Translate, { contentKey: \"home.title\" }, \"Welcome, Java Hipster!\")),\n                React.createElement(\"p\", { className: \"lead\" },\n                    React.createElement(react_jhipster_1.Translate, { contentKey: \"home.subtitle\" }, \"This is your homepage\")),\n                currentUser && currentUser.login ? (React.createElement(\"div\", null,\n                    React.createElement(\"div\", { className: \"alert alert-success\" },\n                        React.createElement(react_jhipster_1.Translate, { contentKey: \"home.logged.message\", interpolate: { username: currentUser.login } },\n                            \"You are logged in as user \",\n                            currentUser.login,\n                            \".\")))) : (React.createElement(\"div\", null,\n                    React.createElement(\"div\", { className: \"alert alert-warning\" },\n                        React.createElement(react_jhipster_1.Translate, { contentKey: \"global.messages.info.authenticated.prefix\" }, \"If you want to \"),\n                        React.createElement(react_router_dom_1.Link, { to: \"/login\", className: \"alert-link\" },\n                            React.createElement(react_jhipster_1.Translate, { contentKey: \"global.messages.info.authenticated.link\" }, \"sign in\")),\n                        React.createElement(react_jhipster_1.Translate, { contentKey: \"global.messages.info.authenticated.suffix\" },\n                            \", you can try the default accounts:\",\n                            React.createElement(\"br\", null),\n                            \"- Administrator (login=\\\"admin\\\" and password=\\\"admin\\\")\",\n                            React.createElement(\"br\", null),\n                            \"- User (login=\\\"user\\\" and password=\\\"user\\\").\")),\n                    React.createElement(\"div\", { className: \"alert alert-warning\" },\n                        React.createElement(react_jhipster_1.Translate, { contentKey: \"global.messages.info.register.noaccount\" }, \"You do not have an account yet?\"),\n                        \"\\u00A0\",\n                        React.createElement(react_router_dom_1.Link, { to: \"/register\", className: \"alert-link\" },\n                            React.createElement(react_jhipster_1.Translate, { contentKey: \"global.messages.info.register.link\" }, \"Register a new account\"))))),\n                React.createElement(\"p\", null,\n                    React.createElement(react_jhipster_1.Translate, { contentKey: \"home.question\" }, \"If you have any question on JHipster:\")),\n                React.createElement(\"ul\", null,\n                    React.createElement(\"li\", null,\n                        React.createElement(\"a\", { href: \"http://jhipster.github.io/\", target: \"_blank\", rel: \"noopener noreferrer\" },\n                            React.createElement(react_jhipster_1.Translate, { contentKey: \"home.link.homepage\" }, \"JHipster homepage\"))),\n                    React.createElement(\"li\", null,\n                        React.createElement(\"a\", { href: \"http://stackoverflow.com/tags/jhipster/info\", target: \"_blank\", rel: \"noopener noreferrer\" },\n                            React.createElement(react_jhipster_1.Translate, { contentKey: \"home.link.stackoverflow\" }, \"JHipster on Stack Overflow\"))),\n                    React.createElement(\"li\", null,\n                        React.createElement(\"a\", { href: \"https://github.com/jhipster/generator-jhipster/issues?state=open\", target: \"_blank\", rel: \"noopener noreferrer\" },\n                            React.createElement(react_jhipster_1.Translate, { contentKey: \"home.link.bugtracker\" }, \"JHipster bug tracker\"))),\n                    React.createElement(\"li\", null,\n                        React.createElement(\"a\", { href: \"https://gitter.im/jhipster/generator-jhipster\", target: \"_blank\", rel: \"noopener noreferrer\" },\n                            React.createElement(react_jhipster_1.Translate, { contentKey: \"home.link.chat\" }, \"JHipster public chat room\"))),\n                    React.createElement(\"li\", null,\n                        React.createElement(\"a\", { href: \"https://twitter.com/java_hipster\", target: \"_blank\", rel: \"noopener noreferrer\" },\n                            React.createElement(react_jhipster_1.Translate, { contentKey: \"home.link.follow\" }, \"follow @java_hipster on Twitter\")))),\n                React.createElement(\"p\", null,\n                    React.createElement(react_jhipster_1.Translate, { contentKey: \"home.like\" }, \"If you like JHipster, do not forget to give us a star on\"),\n                    ' ',\n                    React.createElement(\"a\", { href: \"https://github.com/jhipster/generator-jhipster\", target: \"_blank\", rel: \"noopener noreferrer\" }, \"Github\"),\n                    \"!\")),\n            React.createElement(\"div\", { className: \"col-md-3 pad\" },\n                React.createElement(\"span\", { className: \"hipster rounded\" }))));\n    };\n    return Home;\n}(React.Component));\nexports.Home = Home;\nvar mapStateToProps = function (storeState) { return ({\n    account: storeState.authentication.account,\n    isAuthenticated: storeState.authentication.isAuthenticated\n}); };\nvar mapDispatchToProps = { getSession: authentication_1.getSession };\nexports.default = react_redux_1.connect(mapStateToProps, mapDispatchToProps)(Home);\n",{"version":3,"file":"/Users/julien/workspace/jhipster-automation/samples/jhipster-sample-app-react/src/main/webapp/app/modules/home/home.tsx","sourceRoot":"","sources":["/Users/julien/workspace/jhipster-automation/samples/jhipster-sample-app-react/node_modules/tslint-loader/index.js!/Users/julien/workspace/jhipster-automation/samples/jhipster-sample-app-react/src/main/webapp/app/modules/home/home.tsx"],"names":[],"mappings":";;;AAAA,sBAAoB;AAEpB,6BAA+B;AAC/B,qDAAwC;AACxC,iDAA2C;AAC3C,2CAAsC;AAEtC,qEAAgE;AAWhE;IAA0B,gCAAsC;IAAhE;QAAA,qEAqGC;QApGC,WAAK,GAAe;YAClB,WAAW,EAAE,KAAI,CAAC,KAAK,CAAC,OAAO;SAChC,CAAC;;IAkGJ,CAAC;IAhGC,iCAAkB,GAAlB;QACE,IAAI,CAAC,KAAK,CAAC,UAAU,EAAE,CAAC;IAC1B,CAAC;IAED,wCAAyB,GAAzB,UAA0B,SAAS;QACjC,IAAI,CAAC,QAAQ,CAAC;YACZ,WAAW,EAAE,SAAS,CAAC,OAAO;SAC/B,CAAC,CAAC;IACL,CAAC;IAED,qBAAM,GAAN;QACU,IAAA,oCAAW,CAAgB;QACnC,OAAO,CACL,6BAAK,SAAS,EAAC,KAAK;YAClB,6BAAK,SAAS,EAAC,UAAU;gBACvB;oBACE,oBAAC,0BAAS,IAAC,UAAU,EAAC,YAAY,6BAAmC,CAClE;gBACL,2BAAG,SAAS,EAAC,MAAM;oBACjB,oBAAC,0BAAS,IAAC,UAAU,EAAC,eAAe,4BAAkC,CACrE;gBACH,WAAW,IAAI,WAAW,CAAC,KAAK,CAAC,CAAC,CAAC,CAClC;oBACE,6BAAK,SAAS,EAAC,qBAAqB;wBAClC,oBAAC,0BAAS,IAAC,UAAU,EAAC,qBAAqB,EAAC,WAAW,EAAE,EAAE,QAAQ,EAAE,WAAW,CAAC,KAAK,EAAE;;4BAC3D,WAAW,CAAC,KAAK;gCAClC,CACR,CACF,CACP,CAAC,CAAC,CAAC,CACF;oBACE,6BAAK,SAAS,EAAC,qBAAqB;wBAClC,oBAAC,0BAAS,IAAC,UAAU,EAAC,2CAA2C,sBAA4B;wBAC7F,oBAAC,uBAAI,IAAC,EAAE,EAAC,QAAQ,EAAC,SAAS,EAAC,YAAY;4BACtC,oBAAC,0BAAS,IAAC,UAAU,EAAC,yCAAyC,cAAoB,CAC9E;wBACP,oBAAC,0BAAS,IAAC,UAAU,EAAC,2CAA2C;;4BAE/D,+BAAM;;4BACN,+BAAM;6EACI,CACR;oBAEN,6BAAK,SAAS,EAAC,qBAAqB;wBAClC,oBAAC,0BAAS,IAAC,UAAU,EAAC,yCAAyC,sCAA4C;;wBAC3G,oBAAC,uBAAI,IAAC,EAAE,EAAC,WAAW,EAAC,SAAS,EAAC,YAAY;4BACzC,oBAAC,0BAAS,IAAC,UAAU,EAAC,oCAAoC,6BAAmC,CACxF,CACH,CACF,CACP;gBACD;oBACE,oBAAC,0BAAS,IAAC,UAAU,EAAC,eAAe,4CAAkD,CACrF;gBAEJ;oBACE;wBACE,2BAAG,IAAI,EAAC,4BAA4B,EAAC,MAAM,EAAC,QAAQ,EAAC,GAAG,EAAC,qBAAqB;4BAC5E,oBAAC,0BAAS,IAAC,UAAU,EAAC,oBAAoB,wBAA8B,CACtE,CACD;oBACL;wBACE,2BAAG,IAAI,EAAC,6CAA6C,EAAC,MAAM,EAAC,QAAQ,EAAC,GAAG,EAAC,qBAAqB;4BAC7F,oBAAC,0BAAS,IAAC,UAAU,EAAC,yBAAyB,iCAAuC,CACpF,CACD;oBACL;wBACE,2BAAG,IAAI,EAAC,kEAAkE,EAAC,MAAM,EAAC,QAAQ,EAAC,GAAG,EAAC,qBAAqB;4BAClH,oBAAC,0BAAS,IAAC,UAAU,EAAC,sBAAsB,2BAAiC,CAC3E,CACD;oBACL;wBACE,2BAAG,IAAI,EAAC,+CAA+C,EAAC,MAAM,EAAC,QAAQ,EAAC,GAAG,EAAC,qBAAqB;4BAC/F,oBAAC,0BAAS,IAAC,UAAU,EAAC,gBAAgB,gCAAsC,CAC1E,CACD;oBACL;wBACE,2BAAG,IAAI,EAAC,kCAAkC,EAAC,MAAM,EAAC,QAAQ,EAAC,GAAG,EAAC,qBAAqB;4BAClF,oBAAC,0BAAS,IAAC,UAAU,EAAC,kBAAkB,sCAA4C,CAClF,CACD,CACF;gBAEL;oBACE,oBAAC,0BAAS,IAAC,UAAU,EAAC,WAAW,+DAAqE;oBAAC,GAAG;oBAC1G,2BAAG,IAAI,EAAC,gDAAgD,EAAC,MAAM,EAAC,QAAQ,EAAC,GAAG,EAAC,qBAAqB,aAE9F;wBACF,CACA;YACN,6BAAK,SAAS,EAAC,cAAc;gBAC3B,8BAAM,SAAS,EAAC,iBAAiB,GAAG,CAChC,CACF,CACP,CAAC;IACJ,CAAC;IACH,WAAC;AAAD,CAAC,AArGD,CAA0B,KAAK,CAAC,SAAS,GAqGxC;AArGY,oBAAI;AAuGjB,IAAM,eAAe,GAAG,UAAA,UAAU,IAAI,OAAA,CAAC;IACrC,OAAO,EAAE,UAAU,CAAC,cAAc,CAAC,OAAO;IAC1C,eAAe,EAAE,UAAU,CAAC,cAAc,CAAC,eAAe;CAC3D,CAAC,EAHoC,CAGpC,CAAC;AAEH,IAAM,kBAAkB,GAAG,EAAE,UAAU,6BAAA,EAAE,CAAC;AAE1C,kBAAe,qBAAO,CAAC,eAAe,EAAE,kBAAkB,CAAC,CAAC,IAAI,CAAC,CAAC","sourcesContent":["import './home.css';\n\nimport * as React from 'react';\nimport { Link } from 'react-router-dom';\nimport { Translate } from 'react-jhipster';\nimport { connect } from 'react-redux';\n\nimport { getSession } from 'app/shared/reducers/authentication';\n\nexport interface IHomeProp {\n  account: any;\n  getSession: Function;\n}\n\nexport interface IHomeState {\n  currentUser: any;\n}\n\nexport class Home extends React.Component<IHomeProp, IHomeState> {\n  state: IHomeState = {\n    currentUser: this.props.account\n  };\n\n  componentWillMount() {\n    this.props.getSession();\n  }\n\n  componentWillReceiveProps(nextProps) {\n    this.setState({\n      currentUser: nextProps.account\n    });\n  }\n\n  render() {\n    const { currentUser } = this.state;\n    return (\n      <div className=\"row\">\n        <div className=\"col-md-9\">\n          <h2>\n            <Translate contentKey=\"home.title\">Welcome, Java Hipster!</Translate>\n          </h2>\n          <p className=\"lead\">\n            <Translate contentKey=\"home.subtitle\">This is your homepage</Translate>\n          </p>\n          {currentUser && currentUser.login ? (\n            <div>\n              <div className=\"alert alert-success\">\n                <Translate contentKey=\"home.logged.message\" interpolate={{ username: currentUser.login }}>\n                  You are logged in as user {currentUser.login}.\n                </Translate>\n              </div>\n            </div>\n          ) : (\n            <div>\n              <div className=\"alert alert-warning\">\n                <Translate contentKey=\"global.messages.info.authenticated.prefix\">If you want to </Translate>\n                <Link to=\"/login\" className=\"alert-link\">\n                  <Translate contentKey=\"global.messages.info.authenticated.link\">sign in</Translate>\n                </Link>\n                <Translate contentKey=\"global.messages.info.authenticated.suffix\">\n                  , you can try the default accounts:\n                  <br />- Administrator (login=&quot;admin&quot; and password=&quot;admin&quot;)\n                  <br />- User (login=&quot;user&quot; and password=&quot;user&quot;).\n                </Translate>\n              </div>\n\n              <div className=\"alert alert-warning\">\n                <Translate contentKey=\"global.messages.info.register.noaccount\">You do not have an account yet?</Translate>&nbsp;\n                <Link to=\"/register\" className=\"alert-link\">\n                  <Translate contentKey=\"global.messages.info.register.link\">Register a new account</Translate>\n                </Link>\n              </div>\n            </div>\n          )}\n          <p>\n            <Translate contentKey=\"home.question\">If you have any question on JHipster:</Translate>\n          </p>\n\n          <ul>\n            <li>\n              <a href=\"http://jhipster.github.io/\" target=\"_blank\" rel=\"noopener noreferrer\">\n                <Translate contentKey=\"home.link.homepage\">JHipster homepage</Translate>\n              </a>\n            </li>\n            <li>\n              <a href=\"http://stackoverflow.com/tags/jhipster/info\" target=\"_blank\" rel=\"noopener noreferrer\">\n                <Translate contentKey=\"home.link.stackoverflow\">JHipster on Stack Overflow</Translate>\n              </a>\n            </li>\n            <li>\n              <a href=\"https://github.com/jhipster/generator-jhipster/issues?state=open\" target=\"_blank\" rel=\"noopener noreferrer\">\n                <Translate contentKey=\"home.link.bugtracker\">JHipster bug tracker</Translate>\n              </a>\n            </li>\n            <li>\n              <a href=\"https://gitter.im/jhipster/generator-jhipster\" target=\"_blank\" rel=\"noopener noreferrer\">\n                <Translate contentKey=\"home.link.chat\">JHipster public chat room</Translate>\n              </a>\n            </li>\n            <li>\n              <a href=\"https://twitter.com/java_hipster\" target=\"_blank\" rel=\"noopener noreferrer\">\n                <Translate contentKey=\"home.link.follow\">follow @java_hipster on Twitter</Translate>\n              </a>\n            </li>\n          </ul>\n\n          <p>\n            <Translate contentKey=\"home.like\">If you like JHipster, do not forget to give us a star on</Translate>{' '}\n            <a href=\"https://github.com/jhipster/generator-jhipster\" target=\"_blank\" rel=\"noopener noreferrer\">\n              Github\n            </a>!\n          </p>\n        </div>\n        <div className=\"col-md-3 pad\">\n          <span className=\"hipster rounded\" />\n        </div>\n      </div>\n    );\n  }\n}\n\nconst mapStateToProps = storeState => ({\n  account: storeState.authentication.account,\n  isAuthenticated: storeState.authentication.isAuthenticated\n});\n\nconst mapDispatchToProps = { getSession };\n\nexport default connect(mapStateToProps, mapDispatchToProps)(Home);\n"]}]}